LICENSE
README.md
app-mem-dumper
setup.cfg
setup.py
appmemdumper/VERSION.txt
appmemdumper/__info__.py
appmemdumper/__init__.py
appmemdumper/memdump.py
appmemdumper/utils.py
appmemdumper.egg-info/PKG-INFO
appmemdumper.egg-info/SOURCES.txt
appmemdumper.egg-info/dependency_links.txt
appmemdumper.egg-info/requires.txt
appmemdumper.egg-info/top_level.txt
appmemdumper/dumpers/__init__.py
appmemdumper/dumpers/application.py
appmemdumper/dumpers/system.py
appmemdumper/dumpers/template.py