Metadata-Version: 2.1
Name: appmemdumper
Version: 2.4.4
Summary: Tool for collecting various forensics artifacts in Windows memory dumps using Volatility and Foremost for common Windows applications
Home-page: https://github.com/dhondta/AppmemDumper
Author: Alexandre D'Hondt
Author-email: alexandre.dhondt@gmail.com
License: AGPLv3
Keywords: tinyscript,forensics,volatility,foremost,triage,artifacts,windows,applications
Platform: UNKNOWN
Classifier: Development Status :: 5 - Production/Stable
Classifier: Environment :: Console
Classifier: Intended Audience :: Developers
Classifier: Intended Audience :: Information Technology
Classifier: Intended Audience :: Other Audience
Classifier: License :: OSI Approved :: GNU Affero General Public License v3 or later (AGPLv3+)
Classifier: Programming Language :: Python :: 2
Classifier: Programming Language :: Python :: 2.7
Classifier: Topic :: Security
Requires-Python: <3,>=2.7
